messages/__init__.py
messages/apc_pb2.py
messages/apc_pb2_grpc.py
apc_core-0.1.13.dist-info/METADATA
apc_core-0.1.13.dist-info/WHEEL
apc_core-0.1.13.dist-info/top_level.txt
apc_core-0.1.13.dist-info/RECORD
