Metadata-Version: 2.1
Name: apc-core
Version: 0.1.13
Summary: APC (Agent Protocol Conductor) core protocol library for decentralized agent orchestration.
Home-page: https://github.com/deepfarkade/apc-protocol
Author: APC Contributors
Project-URL: Documentation, https://github.com/deepfarkade/apc-protocol/blob/main/docs/documentation.md
Project-URL: Source, https://github.com/deepfarkade/apc-protocol
Project-URL: Tracker, https://github.com/deepfarkade/apc-protocol/issues
Classifier: Programming Language :: Python :: 3
Classifier: License :: OSI Approved :: MIT License
Classifier: Operating System :: OS Independent
Classifier: Development Status :: 3 - Alpha
Classifier: Intended Audience :: Developers
Classifier: Topic :: Software Development :: Libraries :: Application Frameworks
Requires-Python: >=3.8
Requires-Dist: grpcio
Requires-Dist: grpcio-tools
Requires-Dist: websockets
Requires-Dist: redis
Requires-Dist: boto3
